fastapi_paginator/__init__.py
fastapi_paginator/_models.py
fastapi_paginator/_paginator.py
fastapi_paginator/py.typed
fastapi_paginator-0.1.4.dist-info/METADATA
fastapi_paginator-0.1.4.dist-info/WHEEL
fastapi_paginator-0.1.4.dist-info/LICENSE
fastapi_paginator-0.1.4.dist-info/RECORD
