Metadata-Version: 2.1
Name: fastapi-paginator
Version: 0.1.4
Summary: Paginator for FastAPI
Home-page: https://github.com/JGoutin/fastapi_paginator
License: BSD-2-Clause
Keywords: paginator,fastapi,sqlalchemy
Author: JGoutin
Requires-Python: >=3.10,<4.0
Classifier: Development Status :: 4 - Beta
Classifier: Framework :: FastAPI
Classifier: Intended Audience :: Developers
Classifier: License :: OSI Approved :: BSD License
Classifier: Programming Language :: Python :: 3
Classifier: Programming Language :: Python :: 3.10
Classifier: Programming Language :: Python :: 3.11
Classifier: Typing :: Typed
Requires-Dist: databases
Requires-Dist: fastapi
Project-URL: Repository, https://github.com/JGoutin/fastapi_paginator
